Metadata-Version: 1.2
Name: asmog
Version: 0.0.6
Summary: Python API for Ampio Smog Sensors
Home-page: https://github.com/kstaniek/python-ampio-smog-api
Author: Klaudiusz Staniek
Author-email: kstaniek@gmail.com
License: Apache License 2.0
Download-URL: https://github.com/kstaniek/python-ampio-smog-api/releases
Keywords: home,automation
Platform: any
Classifier: Development Status :: 4 - Beta
Classifier: Intended Audience :: End Users/Desktop
Classifier: Intended Audience :: Developers
Classifier: License :: OSI Approved :: Apache Software License
Classifier: Operating System :: OS Independent
Classifier: Programming Language :: Python :: 3.5
Classifier: Programming Language :: Python :: 3.6
Classifier: Programming Language :: Python :: 3.7
Classifier: Topic :: Home Automation
Requires-Python: >=3.5.0
